quantscript/CointegrationTest .py
quantscript/ConstructingComprehensive.py
quantscript/Duration.py
quantscript/StatisticalFeatures.py
quantscript/__init__.py
quantscript-0.1.0.dist-info/METADATA
quantscript-0.1.0.dist-info/WHEEL
quantscript-0.1.0.dist-info/top_level.txt
quantscript-0.1.0.dist-info/RECORD
