Metadata-Version: 2.1
Name: quantscript
Version: 0.1.0
Summary: A package for calculating statistical data in finance
Home-page: https://github.com/tonyyang1223/quantscript
Author: tonyyang1223
Author-email: tonyyang1223@gmail.com
License: MIT
Requires-Dist: pandas
Requires-Dist: numpy
Requires-Dist: statsmodels
Requires-Dist: matplotlib
Requires-Dist: scipy
